SoundsLike/DictionaryTools.py
SoundsLike/FuzzyTerm.py
SoundsLike/SoundsLike.py
SoundsLike/__init__.py
SoundsLike-0.0.11.dist-info/LICENSE
SoundsLike-0.0.11.dist-info/METADATA
SoundsLike-0.0.11.dist-info/WHEEL
SoundsLike-0.0.11.dist-info/top_level.txt
SoundsLike-0.0.11.dist-info/RECORD
