Metadata-Version: 2.1
Name: SoundsLike
Version: 0.0.11
Summary: SoundsLike is a python package that helps find words that sound like other words.
Home-page: http://github.com/tal-z/SoundsLike/
Author: Tal Zaken
Author-email: talzaken@gmail.com
License: LICENSE
Platform: UNKNOWN
Requires-Dist: cmudict (>=0.4.4)
Requires-Dist: g2p-en (>=2.1.0)
